weather_analysis_jory_3/__init__.py
weather_analysis_jory_3/data_loader2.py
weather_analysis_jory_3/data_processor.py
weather_analysis_jory_3/weather_analysis.py
weather_analysis_jory_3-0.1.4.dist-info/METADATA
weather_analysis_jory_3-0.1.4.dist-info/WHEEL
weather_analysis_jory_3-0.1.4.dist-info/top_level.txt
weather_analysis_jory_3-0.1.4.dist-info/RECORD
